xapp_protected/__init__.py
xapp_protected/__pycache__/xapp_core.cpython-311.pyc
xapp_protected/__pycache__/xapp_core.cpython-312.pyc
xapp_protected/__pycache__/xapp_core.cpython-313.pyc
xapp_protected/__pycache__/xapp_core.cpython-314.pyc
xapp_protected-0.1.4.dist-info/METADATA
xapp_protected-0.1.4.dist-info/WHEEL
xapp_protected-0.1.4.dist-info/top_level.txt
xapp_protected-0.1.4.dist-info/RECORD
