Metadata-Version: 2.4
Name: xapp-protected
Version: 0.1.4
Summary: Protected XApp core module
Home-page: https://github.com/ibrahimkhan008
Author: Mr Void
License: MIT
Project-URL: Homepage, https://github.com/ibrahimkhan008
Requires-Python: >=3.8
Requires-Dist: Flask>=2.3.0
Requires-Dist: pycryptodome>=3.18.0
Requires-Dist: requests>=2.31.0
Requires-Dist: PyJWT>=2.8.0
Requires-Dist: protobuf>=4.23.0
Dynamic: home-page
Dynamic: requires-python
